risk_manager.py
enums/__init__.py
enums/risk_signal_types.py
example/__init__.py
example/datafeed.py
example/main.py
example/strategy.py
strategies/test_balance.py
strategies/test_bbo.py
strategies/test_leverage.py
strategies/test_utils/order_manager.py
strategies/test_utils/position_manager.py
strategies/test_utils/statistics.py
unittest/test_global_level.py
unittest/test_order_level_checks.py
unittest/test_order_quality_risk.py
unittest/test_order_receipt_risk.py
unittest/test_tick_level.py
usecase/__init__.py
usecase/order_quality_scenarios.py
usecase/order_receipt_scenarios.py
usecase/global_level/__init__.py
usecase/global_level/balance_check.py
usecase/global_level/commission_check.py
usecase/global_level/exposure_check.py
usecase/global_level/leverage_check.py
usecase/global_level/position_check.py
usecase/order_level/__init__.py
usecase/order_level/exchange_order_check.py
usecase/order_level/symbol_order_check.py
usecase/tick_level/__init__.py
usecase/tick_level/latency_check.py
usecase/tick_level/spread_check.py
utils/__init__.py
utils/loader.py
utils/order_manager.py
utils/position_manager.py
utils/risk_signal.py
utils/signal_manager.py
utils/statistics.py
utils/trader.py
oq_riskmanager-0.1.12.dist-info/METADATA
oq_riskmanager-0.1.12.dist-info/WHEEL
oq_riskmanager-0.1.12.dist-info/top_level.txt
oq_riskmanager-0.1.12.dist-info/RECORD
