Metadata-Version: 2.4
Name: oq-riskmanager
Version: 0.1.12
Summary: Hedge arbitrage risk management (对冲套利策略风控模块)
Author-email: Yosen <yc1181589856@gmail.com>
License: MIT
Project-URL: Homepage, https://example.com/oq-riskmanager
Classifier: Programming Language :: Python :: 3
Classifier: Programming Language :: Python :: 3 :: Only
Classifier: Programming Language :: Python :: 3.10
Classifier: License :: OSI Approved :: MIT License
Classifier: Operating System :: OS Independent
Requires-Python: >=3.10
Requires-Dist: toml>=0.10.2
